isosplit/__init__.py
isosplit/core.py
isosplit/estimate_density_dip.py
isosplit/isosplit_verbose.py
isosplit-0.1.4.dist-info/METADATA
isosplit-0.1.4.dist-info/WHEEL
isosplit-0.1.4.dist-info/top_level.txt
isosplit-0.1.4.dist-info/RECORD
