Metadata-Version: 2.4
Name: isosplit
Version: 0.1.4
Summary: IsoSplit clustering algorithm for automatic cluster detection
Author: Jeremy Magland
License: Apache-2.0
Project-URL: Homepage, https://github.com/magland/isosplit
Requires-Python: >=3.8
Requires-Dist: numpy
Requires-Dist: scikit-learn
Requires-Dist: scipy
